 {

    "AdminRejected": { "color": "blue","status": -1 },
    "RiderCancelled": { "color": "pink", "status": 0 },
    "Pending": { "color": "orange" , "status": 1 },
    "AdminAccepted": { "color": "grey", "status": 2 },
    "RiderAccepted": { "color": "red", "status": 3, "label": "Accept", "flag": "rider", "icon":"MdOutlineDeliveryDining"},
    "Picked Up": { "color": "aqua", "status": 4 ,"label": "Pick Up", "icon": "GiAirplaneArrival"},
    "Takeaway Success": { "color": "yellow", "status": 5, "label": "Takeaway Success", "icon": "BiMobileAlt" }
}


